gdt/missions/maxi/__init__.py
gdt/missions/maxi/attitude.py
gdt/missions/maxi/finders.py
gdt/missions/maxi/frame.py
gdt/missions/maxi/headers.py
gdt/missions/maxi/orbit.py
gdt/missions/maxi/plot.py
gdt/missions/maxi/time.py
gdt/missions/maxi/gsc/__init__.py
gdt/missions/maxi/gsc/catalogs.py
gdt/missions/maxi/gsc/detectors.py
gdt/missions/maxi/gsc/finders.py
gdt/missions/maxi/gsc/headers.py
gdt/missions/maxi/gsc/response.py
gdt/missions/maxi/gsc/tte.py
astro_gdt_maxi-1.0.1.dist-info/METADATA
astro_gdt_maxi-1.0.1.dist-info/WHEEL
astro_gdt_maxi-1.0.1.dist-info/license.txt
astro_gdt_maxi-1.0.1.dist-info/top_level.txt
astro_gdt_maxi-1.0.1.dist-info/RECORD
